swarmauri_crypto_nacl_pkcs11/NaClPkcs11Crypto.py
swarmauri_crypto_nacl_pkcs11/__init__.py
swarmauri_crypto_nacl_pkcs11-0.3.0.dev4.dist-info/LICENSE
swarmauri_crypto_nacl_pkcs11-0.3.0.dev4.dist-info/METADATA
swarmauri_crypto_nacl_pkcs11-0.3.0.dev4.dist-info/WHEEL
swarmauri_crypto_nacl_pkcs11-0.3.0.dev4.dist-info/entry_points.txt
swarmauri_crypto_nacl_pkcs11-0.3.0.dev4.dist-info/RECORD
